lexedata/__init__.py
lexedata/cli.py
lexedata/error_handling.py
lexedata/types.py
lexedata/data/clics3-network.gml.zip
lexedata/data/example-bantu.xlsx
lexedata/edit/__init__.py
lexedata/edit/_cognate_code_language.py
lexedata/edit/add_central_concepts.py
lexedata/edit/add_cognate_table.py
lexedata/edit/add_concepticon.py
lexedata/edit/add_metadata.py
lexedata/edit/add_segments.py
lexedata/edit/add_singleton_cognatesets.py
lexedata/edit/add_status_column.py
lexedata/edit/add_table.py
lexedata/edit/align.py
lexedata/edit/change_id_column.py
lexedata/edit/clean_forms.py
lexedata/edit/detect_cognates.py
lexedata/edit/merge_cognate_sets.py
lexedata/edit/merge_homophones.py
lexedata/edit/normalize_unicode.py
lexedata/edit/replace_id.py
lexedata/edit/replace_id_column.py
lexedata/edit/simplify_ids.py
lexedata/exporter/__init__.py
lexedata/exporter/cognates.py
lexedata/exporter/edictor.py
lexedata/exporter/matrix.py
lexedata/exporter/phylogenetics.py
lexedata/importer/__init__.py
lexedata/importer/cognates.py
lexedata/importer/edictor.py
lexedata/importer/excel_interleaved.py
lexedata/importer/excel_long_format.py
lexedata/importer/excel_matrix.py
lexedata/report/__init__.py
lexedata/report/coverage.py
lexedata/report/extended_cldf_validate.py
lexedata/report/filter.py
lexedata/report/homophones.py
lexedata/report/judgements.py
lexedata/report/nonconcatenative_morphemes.py
lexedata/report/segment_inventories.py
lexedata/util/__init__.py
lexedata/util/add_metadata.py
lexedata/util/excel.py
lexedata/util/fs.py
lexedata/util/simplify_ids.py
lexedata-1.0.1.dist-info/LICENSE
lexedata-1.0.1.dist-info/METADATA
lexedata-1.0.1.dist-info/WHEEL
lexedata-1.0.1.dist-info/top_level.txt
lexedata-1.0.1.dist-info/RECORD
